README.md
setup.py
alibabacloud_eventbridge_util/__init__.py
alibabacloud_eventbridge_util/client.py
alibabacloud_eventbridge_util.egg-info/PKG-INFO
alibabacloud_eventbridge_util.egg-info/SOURCES.txt
alibabacloud_eventbridge_util.egg-info/dependency_links.txt
alibabacloud_eventbridge_util.egg-info/top_level.txt